MANIFEST.in
README.rst
setup.py
metzoo/__init__.py
metzoo/metzoo.py
metzoo.egg-info/PKG-INFO
metzoo.egg-info/SOURCES.txt
metzoo.egg-info/dependency_links.txt
metzoo.egg-info/not-zip-safe
metzoo.egg-info/requires.txt
metzoo.egg-info/top_level.txt
test/test.py